COPYING
MANIFEST.in
README.md
setup.cfg
setup.py
wcurve.py
docs/Makefile
docs/conf.py
docs/index.rst
docs/make.bat
examples/dh.py
examples/ecdsa.py
examples/run.sh
tests/openssl_ec.c
tests/run.sh
tests/setup.cfg
tests/setup.py
tests/wcurve_unittest.py
wcurve.egg-info/PKG-INFO
wcurve.egg-info/SOURCES.txt
wcurve.egg-info/dependency_links.txt
wcurve.egg-info/top_level.txt